geniverse_hub/__init__.py
geniverse_hub/hub_config.py
geniverse_hub/hub_utils.py
geniverse_hub-0.0.6.dist-info/LICENSE
geniverse_hub-0.0.6.dist-info/METADATA
geniverse_hub-0.0.6.dist-info/WHEEL
geniverse_hub-0.0.6.dist-info/top_level.txt
geniverse_hub-0.0.6.dist-info/RECORD
