Metadata-Version: 2.1
Name: geniverse_hub
Version: 0.0.6
Summary: Library for downloading and loading generative AI models.
Home-page: https://github.com/thegeniverse/geniverse_hub
Author: Javi and Vicc
Author-email: vipermu97@gmail.com
License: UNKNOWN
Project-URL: Docs, https://github.com/thegeniverse/geniverse_hub/docs
Platform: UNKNOWN
Classifier: Programming Language :: Python :: 3
Classifier: License :: OSI Approved :: MIT License
Classifier: Operating System :: OS Independent
Requires-Python: >=3.6
License-File: LICENSE
